sqlmodel_crud_manager/__init__.py
sqlmodel_crud_manager/crud.py
sqlmodel_crud_manager/decorator.py
sqlmodel_crud_manager-0.1.12.dist-info/LICENSE
sqlmodel_crud_manager-0.1.12.dist-info/METADATA
sqlmodel_crud_manager-0.1.12.dist-info/WHEEL
sqlmodel_crud_manager-0.1.12.dist-info/RECORD
