Metadata-Version: 2.1
Name: SQLModel-CRUD-manager
Version: 0.1.12
Summary: The SQLModel CRUD Manager is a Python library that facilitates common Create, Read, Update, and Delete (CRUD) operations on SQLModel entities within a FastAPI application. This library simplifies database interactions and provides an easy-to-use interface for managing SQLModel entities.
Home-page: https://github.com/EChachati/SQLModel-CRUD-manager
License: MIT
Author: Edkar Chachati
Author-email: chachati28@gmail.com
Requires-Python: >=3.10,<4.0
Classifier: License :: OSI Approved :: MIT License
Classifier: Programming Language :: Python :: 3
Classifier: Programming Language :: Python :: 3.10
Classifier: Programming Language :: Python :: 3.11
Classifier: Programming Language :: Python :: 3.12
Requires-Dist: fastapi (>=0.105.0,<0.106.0)
Requires-Dist: sqlmodel (>=0.0.14,<0.0.15)
Project-URL: Documentation, https://github.com/EChachati/SQLModel-CRUD-manager/blob/master/README.md
Project-URL: Repository, https://github.com/EChachati/SQLModel-CRUD-manager
